hypercoil_examples/__init__.py
hypercoil_examples/data/.DS_Store
hypercoil_examples/data/confounds/desc-confounds_timeseries.json
hypercoil_examples/data/confounds/desc-confounds_timeseries.tsv
hypercoil_examples/data/surf/somatomotor.gii
hypercoil_examples/data/surf/somatomotor.nii
hypercoil_examples/data/synthetic/extra-tsv/missingdata.tsv
hypercoil_examples/data/synthetic/extra-tsv/rundata.tsv
hypercoil_examples/data/synthetic/extra-tsv/subdata.tsv
hypercoil_examples/data/synthetic/extra-tsv/subrundata.tsv
hypercoil_examples/data/synthetic/synth-regts/atlas-schaefer400_desc-synth_cov.tsv
hypercoil_examples/data/synthetic/synth-regts/atlas-schaefer400_desc-synth_spec.tsv
hypercoil_examples/data/synthetic/synth-regts/atlas-schaefer400_desc-synth_ts.tsv
hypercoil_examples/synthetic/__init__.py
hypercoil_examples/synthetic/experiments/__init__.py
hypercoil_examples/synthetic/experiments/atlas.py
hypercoil_examples/synthetic/experiments/corr.py
hypercoil_examples/synthetic/experiments/denoise.py
hypercoil_examples/synthetic/experiments/fft.py
hypercoil_examples/synthetic/experiments/overfit_plot.py
hypercoil_examples/synthetic/experiments/run.py
hypercoil_examples/synthetic/experiments/sylo.py
hypercoil_examples/synthetic/experiments/config/layer-atlas_expt-hierarchical25.json
hypercoil_examples/synthetic/experiments/config/layer-atlas_expt-hierarchical5.json
hypercoil_examples/synthetic/experiments/config/layer-atlas_expt-homology.json
hypercoil_examples/synthetic/experiments/config/layer-atlas_expt-unsupervisedhard.json
hypercoil_examples/synthetic/experiments/config/layer-atlas_expt-unsupervisedsoft.json
hypercoil_examples/synthetic/experiments/config/layer-corr_expt-parcellationgroup.json
hypercoil_examples/synthetic/experiments/config/layer-corr_expt-parcellationsub.json
hypercoil_examples/synthetic/experiments/config/layer-corr_expt-stateident.json
hypercoil_examples/synthetic/experiments/config/layer-denoise_expt-batch12.json
hypercoil_examples-0.0.0.post3.dist-info/LICENSE
hypercoil_examples-0.0.0.post3.dist-info/METADATA
hypercoil_examples-0.0.0.post3.dist-info/WHEEL
hypercoil_examples-0.0.0.post3.dist-info/top_level.txt
hypercoil_examples-0.0.0.post3.dist-info/RECORD
