Metadata-Version: 2.1
Name: hypercoil-examples
Version: 0.0.0.post3
Summary: Examples for hypercoil
Author-email: Rastko Ciric <rastko@stanford.edu>
Maintainer-email: Rastko Ciric <rastko@stanford.edu>
License: Apache License
Project-URL: Homepage, https://github.com/hypercoil/hypercoil-examples
Classifier: Programming Language :: Python :: 3
Classifier: License :: OSI Approved :: Apache Software License
Classifier: Operating System :: POSIX :: Linux
Classifier: Operating System :: MacOS :: MacOS X
Requires-Python: >=3.10
License-File: LICENSE
Requires-Dist: click
Requires-Dist: hypercoil
